smart_path/__init__.py
smart_path/__version__.py
smart_path-1.0.1.dist-info/METADATA
smart_path-1.0.1.dist-info/WHEEL
smart_path-1.0.1.dist-info/top_level.txt
smart_path-1.0.1.dist-info/RECORD
