Metadata-Version: 2.1
Name: smart-path
Version: 1.0.1
Summary: Smart dispatch between pathlib.Path and s3path.S3Path. It was borrowed from the project by EMTF: emtf@megvii.com
Home-page: https://github.com/wanzysky/smart_path
Author: Zhaoyi Wan
Author-email: i@wanzy.me
License: UNKNOWN
Platform: UNKNOWN
Classifier: Programming Language :: Python :: 3
Classifier: License :: OSI Approved :: MIT License
Classifier: Operating System :: OS Independent
Classifier: Intended Audience :: Developers
Classifier: Intended Audience :: Science/Research
Classifier: Topic :: Scientific/Engineering :: Artificial Intelligence
Classifier: Topic :: Software Development :: Libraries :: Python Modules
Requires-Python: >=3.5
Requires-Dist: boto3 (>=1.7.47)
Requires-Dist: s3path
